scraptor.py
scraptor-0.5.0.dist-info/WHEEL
scraptor-0.5.0.dist-info/DESCRIPTION.rst
scraptor-0.5.0.dist-info/top_level.txt
scraptor-0.5.0.dist-info/metadata.json
scraptor-0.5.0.dist-info/METADATA
scraptor-0.5.0.dist-info/RECORD
